loggoblocks/__init__.py
loggoblocks/loggoblocks.py
loggoblocks/loggoblocks_archived.py
LoggoBlocks-0.1.2.dist-info/METADATA
LoggoBlocks-0.1.2.dist-info/WHEEL
LoggoBlocks-0.1.2.dist-info/top_level.txt
LoggoBlocks-0.1.2.dist-info/RECORD
