Metadata-Version: 2.1
Name: LoggoBlocks
Version: 0.1.2
Summary: Logging abstraction
Home-page: https://github.com/MoronicGoat/loggoblocks.git
Author: Brian Towner
Author-email: briantwnr47@gmail.com
License: MIT License
Classifier: Programming Language :: Python :: 3
Classifier: Programming Language :: Python :: 3.6
Classifier: Programming Language :: Python :: 3.7
Classifier: Programming Language :: Python :: 3.8
Classifier: Programming Language :: Python :: 3.9
Classifier: Programming Language :: Python :: 3.10
Classifier: License :: OSI Approved :: MIT License
Classifier: Operating System :: OS Independent
Requires-Dist: pyyaml
